surrogate_index/__about__.py
surrogate_index/__init__.py
surrogate_index/_logging.py
surrogate_index/eif.py
surrogate_index/learners.py
surrogate_index/preprocess.py
surrogate_index/py.typed
surrogate_index-0.4.0.dist-info/METADATA
surrogate_index-0.4.0.dist-info/WHEEL
surrogate_index-0.4.0.dist-info/licenses/LICENSE.txt
surrogate_index-0.4.0.dist-info/RECORD
