Metadata-Version: 2.4
Name: surrogate-index
Version: 0.4.0
Summary: Efficient-Influence-Function (EIF) utilities for surrogate-index causal inference.
Project-URL: Homepage, https://github.com/kideokkwon/surrogate-index
Project-URL: Documentation, https://github.com/kideokkwon/surrogate-index#readme
Project-URL: Issues, https://github.com/kideokkwon/surrogate-index/issues
Project-URL: Source, https://github.com/kideokkwon/surrogate-index
Author-email: Kideok Kwon <kideokk16@gmail.com>
License: MIT
License-File: LICENSE.txt
Classifier: Development Status :: 4 - Beta
Classifier: Intended Audience :: Science/Research
Classifier: License :: OSI Approved :: MIT License
Classifier: Operating System :: OS Independent
Classifier: Programming Language :: Python
Classifier: Programming Language :: Python :: 3
Classifier: Programming Language :: Python :: 3 :: Only
Classifier: Programming Language :: Python :: 3.10
Classifier: Programming Language :: Python :: 3.11
Classifier: Programming Language :: Python :: 3.12
Classifier: Programming Language :: Python :: Implementation :: CPython
Classifier: Topic :: Scientific/Engineering :: Mathematics
Requires-Python: >=3.10
Requires-Dist: numpy>=1.26
Requires-Dist: pandas>=2.2
Requires-Dist: scikit-learn>=1.4
Provides-Extra: dev
Requires-Dist: black>=24.3; extra == 'dev'
Requires-Dist: mypy>=1.9; extra == 'dev'
Requires-Dist: pandas-stubs>=2.1.1.230316; extra == 'dev'
Requires-Dist: pytest>=8.1.1; extra == 'dev'
Requires-Dist: ruff>=0.4; extra == 'dev'
Provides-Extra: ml
Requires-Dist: xgboost>=2.0; extra == 'ml'
